gqt/__init__.py
gqt/__main__.py
gqt/database.py
gqt/endpoint.py
gqt/query_builder.py
gqt/screen.py
gqt/tree.py
gqt/version.py
gqt-0.125.6.dist-info/licenses/LICENSE
gqt-0.125.6.dist-info/METADATA
gqt-0.125.6.dist-info/WHEEL
gqt-0.125.6.dist-info/entry_points.txt
gqt-0.125.6.dist-info/top_level.txt
gqt-0.125.6.dist-info/RECORD
