Metadata-Version: 2.4
Name: gqt
Version: 0.125.6
Summary: GraphQL client in the terminal.
Home-page: https://github.com/eerimoq/gqt
Author: Erik Moqvist
Author-email: erik.moqvist@gmail.com
License: MIT
License-File: LICENSE
Requires-Dist: requests
Requires-Dist: xdg
Requires-Dist: pyyaml
Requires-Dist: readlike
Requires-Dist: graphql-core
Requires-Dist: tabulate
Dynamic: author
Dynamic: author-email
Dynamic: description
Dynamic: home-page
Dynamic: license
Dynamic: license-file
Dynamic: requires-dist
Dynamic: summary
